pytreemap/__init__.py
pytreemap/tree_map.py
pytreemap/tree_set.py
pytreemap/abstract/__init__.py
pytreemap/abstract/abstract_collection.py
pytreemap/abstract/abstract_map.py
pytreemap/abstract/abstract_set.py
pytreemap/abstract/collection.py
pytreemap/abstract/map.py
pytreemap/abstract/navigable_map.py
pytreemap/abstract/navigable_set.py
pytreemap/abstract/set.py
pytreemap/abstract/sorted_map.py
pytreemap/abstract/sorted_set.py
pytreemap/tree_map_inner_class/__init__.py
pytreemap/tree_map_inner_class/ascending_sub_map.py
pytreemap/tree_map_inner_class/descending_key_iterator.py
pytreemap/tree_map_inner_class/descending_sub_map.py
pytreemap/tree_map_inner_class/entry.py
pytreemap/tree_map_inner_class/entry_iterator.py
pytreemap/tree_map_inner_class/entry_set.py
pytreemap/tree_map_inner_class/key_iterator.py
pytreemap/tree_map_inner_class/key_set.py
pytreemap/tree_map_inner_class/navigable_sub_map.py
pytreemap/tree_map_inner_class/private_entry_iterator.py
pytreemap/tree_map_inner_class/value_iterator.py
pytreemap/tree_map_inner_class/values.py
pytreemap-0.6.dist-info/LICENSE
pytreemap-0.6.dist-info/METADATA
pytreemap-0.6.dist-info/WHEEL
pytreemap-0.6.dist-info/top_level.txt
pytreemap-0.6.dist-info/RECORD
