Metadata-Version: 2.1
Name: pytreemap
Version: 0.6
Summary: Python Implementation of Java TreeMap/TreeSet
Home-page: https://github.com/GavinPHR/pytreemap
Author-email: gavinsweden@gmail.com
License: gpl-2.0
Keywords: python3,self-balancing,binary-search-tree,red-black-tree,java,treemap,treeset
Classifier: Programming Language :: Python :: 3
Classifier: Development Status :: 4 - Beta
Classifier: Intended Audience :: Developers
Classifier: Topic :: Software Development :: Libraries :: Python Modules
Classifier: License :: OSI Approved :: GNU General Public License v2 (GPLv2)
Requires-Python: >=3.5
License-File: LICENSE
